{"title": "やわらかな決意は都市に溶けて", "lines": [{"start": 29.72, "end": 29.86, "ja": "", "ko_pron": "", "ko": "", "tag": "Intro - instrumental"}, {"start": 29.86, "end": 59.62, "ja": "朝のアパートの廊下を抜けて 静かにスニーカー踏みしめる", "ko_pron": "", "ko": "", "tag": "Verse 1"}, {"start": 59.62, "end": 59.74, "ja": "カーブの先 まだ見えない期待に手を伸ばしてみる", "ko_pron": "", "ko": "", "tag": "Pre-Chorus"}, {"start": 59.74, "end": 59.86, "ja": "残した昨日のメモはもういらないから", "ko_pron": "", "ko": "", "tag": "Line 4"}, {"start": 59.86, "end": 65.38, "ja": "交差点の光が揺れても 眼差しはまっすぐ進む", "ko_pron": "", "ko": "", "tag": "Chorus"}, {"start": 65.38, "end": 93.12, "ja": "迷いの跡を振り返らずに 少しずつ速く歩き出す", "ko_pron": "", "ko": "", "tag": "Line 6"}, {"start": 93.12, "end": 100.72, "ja": "コンビニの袋 握りしめて いつもの坂を登りきって", "ko_pron": "", "ko": "", "tag": "Verse 2"}, {"start": 100.72, "end": 100.82, "ja": "乾いたアスファルトの匂いに混ざる 新しい季節感じて", "ko_pron": "", "ko": "", "tag": "Line 8"}, {"start": 100.84, "end": 101.94, "ja": "カーブの先 まだ見えない期待に手を伸ばしてみる", "ko_pron": "", "ko": "", "tag": "Pre-Chorus"}, {"start": 101.94, "end": 107.12, "ja": "残した昨日のメモはもういらないから", "ko_pron": "", "ko": "", "tag": "Line 10"}, {"start": 107.12, "end": 112.94, "ja": "交差点の光が揺れても 眼差しはまっすぐ進む", "ko_pron": "", "ko": "", "tag": "Chorus"}, {"start": 112.94, "end": 120.1, "ja": "迷いの跡を振り返らずに 少しずつ速く歩き出す", "ko_pron": "", "ko": "", "tag": "Line 12"}, {"start": 120.1, "end": 162.14, "ja": "錆びかけた自転車置き場で ひとつ深呼吸してから", "ko_pron": "", "ko": "", "tag": "Bridge"}, {"start": 162.14, "end": 164.98, "ja": "背中の荷物 少し軽くしたら 新しいルール胸に刻む", "ko_pron": "", "ko": "", "tag": "Line 14"}, {"start": 164.98, "end": 176.34, "ja": "交差点の光が揺れても 眼差しはまっすぐ進む", "ko_pron": "", "ko": "", "tag": "Final Chorus"}, {"start": 176.34, "end": 176.9, "ja": "迷いの跡を振り返らずに 少しずつ速く歩き出す", "ko_pron": "", "ko": "", "tag": "Line 16"}, {"start": 176.9, "end": 221.24, "ja": "ささやかな決意は都市の音に溶けていく", "ko_pron": "", "ko": "", "tag": "Line 17"}, {"start": 221.24, "end": 222.2, "ja": "今だけのリズム 体ごと任せて 明日を選んでいく", "ko_pron": "", "ko": "", "tag": "Line 18"}, {"start": 222.2, "end": 224.82, "ja": "輝くビルのガラスに映る自分を見送りながら", "ko_pron": "", "ko": "", "tag": "Outro"}]}