{"title": "Forward Loop Cinema", "lines": [{"start": 0.0, "end": 0.78, "ja": "昨日の地面に残したノートパソコンの跡がまだ消えない", "ko_pron": "", "ko": "", "tag": "Verse 1"}, {"start": 0.9, "end": 0.96, "ja": "", "ko_pron": "", "ko": "", "tag": "Intro - instrumental"}, {"start": 11.64, "end": 18.64, "ja": "走る自転車のベルが遠くで響いている 夢中で追いかける理由はひとつだけ", "ko_pron": "", "ko": "", "tag": "Pre-Chorus"}, {"start": 26.78, "end": 33.78, "ja": "交差点の手前で足を止めて　今日の続きを思い出す　雲の切れ間に差し込む光みたいな気分で", "ko_pron": "", "ko": "", "tag": "Chorus"}, {"start": 41.72, "end": 48.72, "ja": "ボタンをかけ直して背筋を伸ばし　ありふれた看板を横目に歩く", "ko_pron": "", "ko": "", "tag": "Verse 2"}, {"start": 53.46, "end": 60.46, "ja": "走る自転車のベルが遠くで響いている 夢中で追いかける理由はひとつだけ", "ko_pron": "", "ko": "", "tag": "Pre-Chorus"}, {"start": 67.84, "end": 74.84, "ja": "交差点の手前で足を止めて　今日の続きを思い出す　雲の切れ間に差し込む光みたいな気分で", "ko_pron": "", "ko": "", "tag": "Chorus"}, {"start": 83.48, "end": 90.48, "ja": "誰も知らない場所で小さく深呼吸する 置いてきた荷物よりも軽やかになる瞬間を選ぶ", "ko_pron": "", "ko": "", "tag": "Bridge"}, {"start": 100.88, "end": 107.88, "ja": "交差点の手前で足を止めて　今日の続きを思い出す　雲の切れ間に差し込む光みたいな気分で　昨日の迷いがシャツの袖口から抜けていく　新しい一歩を踏み出す音が胸に残る", "ko_pron": "", "ko": "", "tag": "Final Chorus"}, {"start": 120.0, "end": 127.0, "ja": "シャッターの隙間からこぼれる午後の光が　僕の影を優しく照らしてくれる", "ko_pron": "", "ko": "", "tag": "Outro"}], "meta": {"timing_clamped": true, "max_line_dur_sec": 7.0, "gap_sec": 0.12, "min_dur_sec": 0.06, "changed_items": 17, "clipped_by_next": 8, "clipped_by_maxdur": 8}}