{"title": "パステルのままエネルギーリセット", "lines": [{"start": 0.94, "end": 23.78, "ja": "", "ko_pron": "", "ko": "", "tag": "Intro - instrumental"}, {"start": 23.78, "end": 32.78, "ja": "目覚ましが鳴ってソファから飛び出す朝の瞬間", "ko_pron": "", "ko": "", "tag": "Verse 1"}, {"start": 32.78, "end": 48.16, "ja": "ふわふわのスリッパで廊下をすべってみる新しい気分", "ko_pron": "", "ko": "", "tag": "Pre-Chorus"}, {"start": 48.16, "end": 59.22, "ja": "眠ってたエネルギー集めて今日も走りだすリセットの魔法", "ko_pron": "", "ko": "", "tag": "Chorus"}, {"start": 59.22, "end": 70.36, "ja": "冷蔵庫を開けてヨーグルトを選ぶ小さな決意", "ko_pron": "", "ko": "", "tag": "Verse 2"}, {"start": 70.36, "end": 101.18, "ja": "ひとくち食べたら心の充電満タンまで戻る", "ko_pron": "", "ko": "", "tag": "Pre-Chorus"}, {"start": 101.18, "end": 115.76, "ja": "眠ってたエネルギー集めて今日も走りだすリセットの魔法", "ko_pron": "", "ko": "", "tag": "Chorus"}, {"start": 115.76, "end": 129.62, "ja": "本棚の隅に忘れてたメモを拾い上げて笑う", "ko_pron": "", "ko": "", "tag": "Bridge"}, {"start": 129.62, "end": 144.56, "ja": "眠ってたエネルギー集めて今日も走りだすリセットの魔法 夢中な午後も未来へ続くステップになる", "ko_pron": "", "ko": "", "tag": "Final Chorus"}, {"start": 144.56, "end": 155.1, "ja": "靴を履き替えて玄関の光へと踏み出すリズムで", "ko_pron": "", "ko": "", "tag": "Outro"}]}